{
  "dynamics": [
    {
      "id": "DD-001",
      "name": "Elementary",
      "gradeBand": "Elementary",
      "parentEmotionalLens": "Protection and innocence",
      "commonParentFear": "My child is emotionally unsafe or misunderstood",
      "typicalEscalationStyle": "Highly emotional and protective",
      "typicalLeadershipChallenge": "Separating behavior from identity without sounding cold",
      "commonParentLanguage": "\"She’s just a little girl.\" / \"He would never hurt anyone on purpose.\"",
      "mostSensitiveThemes": "Safety; emotional harm; teacher warmth",
      "mostEffectiveLeadershipStyle": "Warmth, reassurance, calm containment",
      "commonTacticalShifts": "High emotional recruitment and guilt projection",
      "notes": "Parents often view children as extensions of innocence",
      "traits": [
        "Protection and innocence",
        "Fear child is emotionally unsafe or misunderstood",
        "Highly emotional and protective",
        "Sensitive themes: safety, emotional harm, teacher warmth",
        "Effective leadership: warmth, reassurance, calm containment"
      ]
    },
    {
      "id": "DD-002",
      "name": "Middle School",
      "gradeBand": "Middle School",
      "parentEmotionalLens": "Fairness, identity, and social survival",
      "commonParentFear": "My child is being targeted, embarrassed, or socially harmed",
      "typicalEscalationStyle": "Rapid emotional swings and fairness arguments",
      "typicalLeadershipChallenge": "Managing emotional volatility and peer-related conflict",
      "commonParentLanguage": "\"There’s more to the story.\" / \"Other kids were involved too.\"",
      "mostSensitiveThemes": "Respect; peer dynamics; fairness; humiliation",
      "mostEffectiveLeadershipStyle": "Calm structure with emotional validation",
      "commonTacticalShifts": "Fast shifts between escalation and cooperation",
      "notes": "Common peak conflict years for schools",
      "traits": ["Fairness and social identity pressure", "Rapid emotional swings", "Sensitive themes: respect, peer dynamics, fairness, humiliation"]
    },
    {
      "id": "DD-003",
      "name": "High School",
      "gradeBand": "High School",
      "parentEmotionalLens": "Future consequences and independence",
      "commonParentFear": "This incident will damage my child’s future",
      "typicalEscalationStyle": "Strategic, defensive, or consequence-focused",
      "typicalLeadershipChallenge": "Balancing realism with hope and professionalism",
      "commonParentLanguage": "\"This could affect college.\" / \"This will go on their record.\"",
      "mostSensitiveThemes": "Suspensions; reputation; graduation; future opportunities",
      "mostEffectiveLeadershipStyle": "Direct realism and calm professionalism",
      "commonTacticalShifts": "Higher negotiation and policy challenges",
      "notes": "Parents often become more image and future focused",
      "traits": ["Future consequences focus", "Strategic/defensive escalation", "Sensitive themes: suspensions, reputation, graduation, future opportunities"]
    },
    {
      "id": "DD-004",
      "name": "Preschool / Early Childhood",
      "gradeBand": "Preschool / Early Childhood",
      "parentEmotionalLens": "Nurturing and emotional safety",
      "commonParentFear": "My child is emotionally traumatized or scared",
      "typicalEscalationStyle": "Intensely protective and emotionally reactive",
      "typicalLeadershipChallenge": "Discussing behavior without sounding harsh or punitive",
      "commonParentLanguage": "\"He’s only four.\" / \"She doesn’t understand yet.\"",
      "mostSensitiveThemes": "Emotional tone; teacher warmth; separation anxiety",
      "mostEffectiveLeadershipStyle": "Gentle reassurance and developmental framing",
      "commonTacticalShifts": "Very high emotional sensitivity",
      "notes": "Common with first-time parents",
      "traits": ["Nurturing and emotional safety lens", "Intensely protective reactivity", "Sensitive themes: emotional tone, teacher warmth, separation anxiety"]
    },
    {
      "id": "DD-005",
      "name": "Transition to Middle School",
      "gradeBand": "Transition to Middle School",
      "parentEmotionalLens": "Loss of control and growing independence",
      "commonParentFear": "My child is changing and I can’t fully protect them anymore",
      "typicalEscalationStyle": "Anxious, hyper-reactive, emotionally inconsistent",
      "typicalLeadershipChallenge": "Helping parents tolerate growing student independence",
      "commonParentLanguage": "\"He’s not acting like himself lately.\"",
      "mostSensitiveThemes": "Social pressure; identity shifts; peer influence",
      "mostEffectiveLeadershipStyle": "Calm guidance and normalization",
      "commonTacticalShifts": "Heightened parent anxiety",
      "notes": "Common during sixth-grade transition",
      "traits": ["Loss of control lens", "Anxious and inconsistent escalation", "Sensitive themes: social pressure, identity shifts, peer influence"]
    },
    {
      "id": "DD-006",
      "name": "Transition to High School",
      "gradeBand": "Transition to High School",
      "parentEmotionalLens": "Future pressure and academic identity",
      "commonParentFear": "My child may fall behind socially or academically",
      "typicalEscalationStyle": "Performance-focused and highly anxious",
      "typicalLeadershipChallenge": "Balancing accountability with long-term perspective",
      "commonParentLanguage": "\"Ninth grade counts now.\"",
      "mostSensitiveThemes": "Grades; social belonging; athletics; future success",
      "mostEffectiveLeadershipStyle": "Structured realism with support-oriented framing",
      "commonTacticalShifts": "Increased academic and identity pressure",
      "notes": "Common in competitive communities",
      "traits": ["Academic identity pressure", "Performance-focused anxiety", "Sensitive themes: grades, belonging, athletics, future success"]
    },
    {
      "id": "DD-007",
      "name": "Senior Year",
      "gradeBand": "Senior Year",
      "parentEmotionalLens": "Consequences and future preservation",
      "commonParentFear": "My child’s opportunities could be permanently damaged",
      "typicalEscalationStyle": "Highly strategic and emotionally charged",
      "typicalLeadershipChallenge": "Managing panic around long-term consequences",
      "commonParentLanguage": "\"Don’t ruin their future over one mistake.\"",
      "mostSensitiveThemes": "Graduation; scholarships; college admissions",
      "mostEffectiveLeadershipStyle": "Calm professionalism and process clarity",
      "commonTacticalShifts": "High negotiation and policy pressure",
      "notes": "Parents often emotionally flooded by future fear",
      "traits": ["Future preservation lens", "Strategic/emotionally charged escalation", "Sensitive themes: graduation, scholarships, college admissions"]
    },
    {
      "id": "DD-008",
      "name": "Special Education / Support Needs",
      "gradeBand": "Special Education / Support Needs",
      "parentEmotionalLens": "Fear of labeling and misunderstanding",
      "commonParentFear": "My child will be judged, limited, or stigmatized",
      "typicalEscalationStyle": "Defensive, emotional, highly sensitive",
      "typicalLeadershipChallenge": "Balancing support conversations with dignity",
      "commonParentLanguage": "\"My child is not broken.\" / \"You’re labeling them.\"",
      "mostSensitiveThemes": "Identity; stigma; fairness; support access",
      "mostEffectiveLeadershipStyle": "Compassionate, nonjudgmental structure",
      "commonTacticalShifts": "Extremely high shame and fear sensitivity",
      "notes": "One of the most emotionally complex areas in schools",
      "traits": ["Labeling/stigma fear", "Defensive and highly sensitive escalation", "Sensitive themes: identity, stigma, fairness, support access"]
    },
    {
      "id": "DD-009",
      "name": "Gifted / High Achievement",
      "gradeBand": "Gifted / High Achievement",
      "parentEmotionalLens": "Status and identity preservation",
      "commonParentFear": "My child’s intelligence or potential is being overlooked",
      "typicalEscalationStyle": "Competitive, analytical, emotionally invested",
      "typicalLeadershipChallenge": "Managing comparison and entitlement dynamics",
      "commonParentLanguage": "\"My child is bored because they’re advanced.\"",
      "mostSensitiveThemes": "Fairness; recognition; opportunity",
      "mostEffectiveLeadershipStyle": "Respectful realism and evidence-based communication",
      "commonTacticalShifts": "High comparison and advocacy behaviors",
      "notes": "Common in achievement-oriented families",
      "traits": ["Status/identity preservation", "Competitive analytical escalation", "Sensitive themes: fairness, recognition, opportunity"]
    },
    {
      "id": "DD-010",
      "name": "Alternative / Behavioral Placement",
      "gradeBand": "Alternative / Behavioral Placement",
      "parentEmotionalLens": "Fear of exclusion and social judgment",
      "commonParentFear": "My child is being pushed out or labeled negatively",
      "typicalEscalationStyle": "Highly defensive and distrustful",
      "typicalLeadershipChallenge": "Maintaining dignity while discussing serious concerns",
      "commonParentLanguage": "\"You’re trying to get rid of my child.\"",
      "mostSensitiveThemes": "Exclusion; labeling; institutional distrust",
      "mostEffectiveLeadershipStyle": "Calm transparency and relationship preservation",
      "commonTacticalShifts": "Extreme escalation potential",
      "notes": "Strong shame and anti-system dynamics common",
      "traits": ["Exclusion/judgment fear", "Highly defensive distrust", "Sensitive themes: exclusion, labeling, institutional distrust"]
    }
  ]
}
